{
    "code": 1,
    "title": "此曰江湖",
    "content": [
        {
            "name": "天涯",
            "qq": 36937883,
            "type": 3,
            "msg": [
                "今天份奇奇怪怪 0616",
                "",
                ""
            ]
        },
        {
            "name": "天涯",
            "qq": 36937883,
            "type": 3,
            "msg": [
                "",
                "https://qqq.gtimg.cn/music/photo_new/T053XD000001hTZJW1Vl7Xf.jpg",
                " 见一面也要付钱？<br>http://yyds-1259597897.cos.ap-chengdu.myqcloud.com/index.html#0616cb96d7fded3bcb75e1909cb9ef7931b5"
            ]
        },
        {
            "name": "天涯",
            "qq": 36937883,
            "type": 3,
            "msg": [
                "",
                "https://qqq.gtimg.cn/music/photo_new/T053XD0000004DF793qu2rL.png",
                "亲生的不生气就是有点恶心。<br>https://5680.net/e435fa2d0c800b0a263019ef6806eb7c39ab2156.m3u8"
            ]
        },
        {
            "name": "天涯",
            "qq": 36937883,
            "type": 3,
            "msg": [
                "",
                "https://qqq.gtimg.cn/music/photo_new/T053XD000001yItEV25EzuL.png",
                "她用了什么东西？有网友知道吗<br>https://5680.net/f1393b1eaae1a181e30f39a02e0d87106871542c.m3u8"
            ]
        },
        {
            "name": "天涯",
            "qq": 36937883,
            "type": 3,
            "msg": [
                "",
                "https://qqq.gtimg.cn/music/photo_new/T053XD0000030XhP2374Fo5.jpg",
                "网传 某地某商业银行的80后女员工出轨60后副行长<br>https://5680.net/54a89cd237569c9570dacbfa49a4faa56f30ce1d.m3u8"
            ]
        },
        {
            "name": "天涯",
            "qq": 36937883,
            "type": 3,
            "msg": [
                "",
                "https://qqq.gtimg.cn/music/photo_new/T053XD000004J3JHh1P6ZRs.png",
                "针灸搞这么深的脏腑针，见过没有？<br>https://5680.net/ef7028b57ced5162c6582b0cb47cebc30d5ffd8e.m3u8"
            ]
        },
        {
            "name": "天涯",
            "qq": 36937883,
            "type": 3,
            "msg": [
                "",
                "https://qqq.gtimg.cn/music/photo_new/T053XD000003PUX0G2dYi2W.png",
                " 大哥有性癖<br>https://5680.net/3b96dac7cd6615d74139885bb7cf6c09b33be4a5.m3u8"
            ]
        },
        {
            "name": "天涯",
            "qq": 36937883,
            "type": 3,
            "msg": [
                "",
                "https://qqq.gtimg.cn/music/photo_new/T053XD000002nXvC32X51Z4.jpg",
                "前脚说澳洲人很亲切后脚就突然被揍了<br>http://yyds-1259597897.cos.ap-chengdu.myqcloud.com/index.html#0616ee5d720c251a12dabbdbec9e5dedc274"
            ]
        },
        {
            "name": "天涯",
            "qq": 36937883,
            "type": 3,
            "msg": [
                "",
                "https://qqq.gtimg.cn/music/photo_new/T053XD000002HGiki3aFEjG.png",
                " 走廊里的饥渴男女<br>https://5680.net/724c9846dd71da452a7b29eafb411114a575eaff.m3u8"
            ]
        },
        {
            "name": "天涯",
            "qq": 36937883,
            "type": 3,
            "msg": [
                "",
                "https://qqq.gtimg.cn/music/photo_new/T053XD000001TXtQz0KPUpM.png",
                " 谁女朋友丢在深山里<br>https://5680.net/9d496fecc5b369d387b6b158397bc07f16f34969.m3u8"
            ]
        },
        {
            "name": "天涯",
            "qq": 36937883,
            "type": 3,
            "msg": [
                "",
                "https://qqq.gtimg.cn/music/photo_new/T053XD000003SLRZE3u0MVV.png",
                "网友探店日记<br>https://5680.net/cea593ec8ba4310be23124eb3288b35c42114836.m3u8<br>https://5680.net/2beedfc21074a018636ddba9bb222a0d79158d88.m3u8<br>https://5680.net/c8c171cdded689c0d5a10e3f6f6fb8777b3827af.m3u8<br>https://5680.net/2cddf67e1310ca900e2f9db44f83a9b177241a7e.m3u8<br>https://5680.net/37a6dfa9a77b53185114c64d095b23e8286a3833.m3u8<br>https://5680.net/8886c0bface3647981aa7c37921cc9065d55254e.m3u8"
            ]
        },
        {
            "name": "天涯",
            "qq": 36937883,
            "type": 3,
            "msg": [
                "",
                "https://qqq.gtimg.cn/music/photo_new/T053XD0000021N6jM1DfDUK.jpg",
                "大四女生实名举报音乐学院书记性骚扰<br>https://5680.net/0de9c9d71b48d04e8f4b16c665eb594bf77bfbdd.m3u8"
            ]
        },
        {
            "name": "天涯",
            "qq": 36937883,
            "type": 3,
            "msg": [
                "",
                "https://qqq.gtimg.cn/music/photo_new/T053XD000003HSN9R3HtY6B.png",
                "哪位网友想体验一下吗<br>https://5680.net/bece26495f972d7f41d0232181817bb06e6283c5.m3u8"
            ]
        },
        {
            "name": "天涯",
            "qq": 36937883,
            "type": 3,
            "msg": [
                "",
                "https://qqq.gtimg.cn/music/photo_new/T053XD000003rEFQc4QyX80.png",
                "女子去夜店点男模没钱支付<br>https://5680.net/4f6c895bfac67e12cce6f49607f7326e109e86c0.m3u8"
            ]
        },
        {
            "name": "天涯",
            "qq": 36937883,
            "type": 3,
            "msg": [
                "",
                "https://qqq.gtimg.cn/music/photo_new/T053XD0000043TCBC24MqxT.jpg",
                "每日趣图<br>http://yyds-1259597897.cos.ap-chengdu.myqcloud.com/index.html#06167377d36fce4c963fde4e22a0b18c18d1"
            ]
        },
        {
            "name": "天涯",
            "qq": 36937883,
            "type": 3,
            "msg": [
                "",
                "https://qqq.gtimg.cn/music/photo_new/T053XD000003NmXs53ditVv.png",
                "每日一捉<br>https://5680.net/db465d59716ca1f0706c4416538e0162d64c545b.m3u8"
            ]
        },
        {
            "name": "天涯",
            "qq": 36937883,
            "type": 3,
            "msg": [
                "",
                "https://qqq.gtimg.cn/music/photo_new/T053XD000000shVjK0mfmBt.jpg",
                "腿控福利<br>http://yyds-1259597897.cos.ap-chengdu.myqcloud.com/index.html#061610160f2a58636ff8e555a1f6b9367739"
            ]
        },
        {
            "name": "天涯",
            "qq": 36937883,
            "type": 3,
            "msg": [
                "",
                "https://qqq.gtimg.cn/music/photo_new/T053XD000001xFSBj1feFbB.png",
                "好活！当赏！<br>https://5680.net/aa24d9ccd21a89b37ad60fea1620a5be68c770e9.m3u8"
            ]
        },
        {
            "name": "天涯",
            "qq": 36937883,
            "type": 3,
            "msg": [
                "",
                "https://qqq.gtimg.cn/music/photo_new/T053XD0000022C2Zo48u8d2.jpg",
                "http://sezywf0lp.hb-bkt.clouddn.com/base?ul=aHR0cDovL3d4MzkuNnl4aS5jb20vaW5kZXguaHRtbCMvcGFnZXMvYXJ0aWNsZS9hcnRpY2xlP2lkPTY2NmU3MDgyODYyMDY2N2JiNDhiMmMzMg=="
            ]
        }
    ]
}