{
    "code": 1,
    "content": [
        {
            "name": "天涯",
            "qq": 36937883,
            "type": 3,
            "msg": [
                "艺术鉴赏",
                "",
                ""
            ]
        },
        {
            "name": "天涯",
            "qq": 36937883,
            "type": 3,
            "msg": [
                "",
                "https://qqq.gtimg.cn/music/photo_new/T053XD0000010XTp23NL3b5.jpg",
                ""
            ]
        },
        {
            "name": "天涯",
            "qq": 36937883,
            "type": 3,
            "msg": [
                "",
                "https://qqq.gtimg.cn/music/photo_new/T053XD000001HWbjC0tnv8p.jpg",
                ""
            ]
        },
        {
            "name": "天涯",
            "qq": 36937883,
            "type": 3,
            "msg": [
                "",
                "https://qqq.gtimg.cn/music/photo_new/T053XD000002RkPwk34GNZ8.jpg",
                ""
            ]
        },
        {
            "name": "天涯",
            "qq": 36937883,
            "type": 3,
            "msg": [
                "",
                "https://qqq.gtimg.cn/music/photo_new/T053XD00000362QlT0dNIUZ.jpg",
                ""
            ]
        },
        {
            "name": "天涯",
            "qq": 36937883,
            "type": 3,
            "msg": [
                "",
                "https://qqq.gtimg.cn/music/photo_new/T053XD000003iZTzz2fjgdW.jpg",
                ""
            ]
        },
        {
            "name": "天涯",
            "qq": 36937883,
            "type": 3,
            "msg": [
                "",
                "https://qqq.gtimg.cn/music/photo_new/T053XD000003xK9bG2NzBaj.jpg",
                ""
            ]
        },
        {
            "name": "天涯",
            "qq": 36937883,
            "type": 3,
            "msg": [
                "",
                "https://qqq.gtimg.cn/music/photo_new/T053XD0000043ApnP4U4gvZ.jpg",
                ""
            ]
        },
        {
            "name": "天涯",
            "qq": 36937883,
            "type": 3,
            "msg": [
                "",
                "https://qqq.gtimg.cn/music/photo_new/T053XD000004WLrDV39w1uE.jpg",
                ""
            ]
        },
        {
            "name": "天涯",
            "qq": 36937883,
            "type": 3,
            "msg": [
                "",
                "https://qqq.gtimg.cn/music/photo_new/T053XD00000041VDo016vu5.jpg",
                ""
            ]
        },
        {
            "name": "天涯",
            "qq": 36937883,
            "type": 3,
            "msg": [
                "",
                "https://qqq.gtimg.cn/music/photo_new/T053XD000003RofJH43rlzC.jpg",
                ""
            ]
        },
        {
            "name": "天涯",
            "qq": 36937883,
            "type": 3,
            "msg": [
                "",
                "https://qqq.gtimg.cn/music/photo_new/T053XD000000jWwao49BizS.jpg",
                ""
            ]
        },
        {
            "name": "天涯",
            "qq": 36937883,
            "type": 3,
            "msg": [
                "",
                "https://qqq.gtimg.cn/music/photo_new/T053XD000000xkvtC2ydP5J.jpg",
                ""
            ]
        },
        {
            "name": "天涯",
            "qq": 36937883,
            "type": 3,
            "msg": [
                "",
                "https://qqq.gtimg.cn/music/photo_new/T053XD0000049pEqq33Fq05.jpg",
                ""
            ]
        },
        {
            "name": "天涯",
            "qq": 36937883,
            "type": 3,
            "msg": [
                "",
                "https://qqq.gtimg.cn/music/photo_new/T053XD000001yrUnL3AN73p.jpg",
                ""
            ]
        },
        {
            "name": "天涯",
            "qq": 36937883,
            "type": 3,
            "msg": [
                "",
                "https://qqq.gtimg.cn/music/photo_new/T053XD000002pR9Lh0bCmSs.jpg",
                ""
            ]
        },
        {
            "name": "天涯",
            "qq": 36937883,
            "type": 3,
            "msg": [
                "",
                "https://qqq.gtimg.cn/music/photo_new/T053XD000003vZ6TQ1qZkEg.jpg",
                ""
            ]
        },
        {
            "name": "天涯",
            "qq": 36937883,
            "type": 3,
            "msg": [
                "",
                "https://qqq.gtimg.cn/music/photo_new/T053XD000003B2pMf3dDKgz.jpg",
                ""
            ]
        },
        {
            "name": "天涯",
            "qq": 36937883,
            "type": 3,
            "msg": [
                "",
                "https://qqq.gtimg.cn/music/photo_new/T053XD000004BzjlC2BqWJJ.jpg",
                ""
            ]
        },
        {
            "name": "天涯",
            "qq": 36937883,
            "type": 3,
            "msg": [
                "",
                "https://qqq.gtimg.cn/music/photo_new/T053XD000001F1msV2gyV15.jpg",
                ""
            ]
        },
        {
            "name": "天涯",
            "qq": 36937883,
            "type": 3,
            "msg": [
                "",
                "https://qqq.gtimg.cn/music/photo_new/T053XD0000017d8wi0Yc2Jn.jpg",
                ""
            ]
        },
        {
            "name": "天涯",
            "qq": 36937883,
            "type": 3,
            "msg": [
                "",
                "https://qqq.gtimg.cn/music/photo_new/T053XD000000bFafS26k7Gq.jpg",
                ""
            ]
        },
        {
            "name": "天涯",
            "qq": 36937883,
            "type": 3,
            "msg": [
                "",
                "https://qqq.gtimg.cn/music/photo_new/T053XD0000027cvWR0Dsrcg.jpg",
                ""
            ]
        },
        {
            "name": "天涯",
            "qq": 36937883,
            "type": 3,
            "msg": [
                "",
                "https://qqq.gtimg.cn/music/photo_new/T053XD000000vndct4NsYqC.jpg",
                ""
            ]
        },
        {
            "name": "天涯",
            "qq": 36937883,
            "type": 3,
            "msg": [
                "",
                "https://qqq.gtimg.cn/music/photo_new/T053XD000004NxbwA2RG0we.jpg",
                ""
            ]
        },
        {
            "name": "天涯",
            "qq": 36937883,
            "type": 3,
            "msg": [
                "",
                "https://qqq.gtimg.cn/music/photo_new/T053XD000004YRxxd3PRC1D.jpg",
                ""
            ]
        },
        {
            "name": "天涯",
            "qq": 36937883,
            "type": 3,
            "msg": [
                "",
                "https://qqq.gtimg.cn/music/photo_new/T053XD0000032jzrB3ICLK3.jpg",
                ""
            ]
        },
        {
            "name": "天涯",
            "qq": 36937883,
            "type": 3,
            "msg": [
                "",
                "https://qqq.gtimg.cn/music/photo_new/T053XD0000037WAc928CGlZ.jpg",
                ""
            ]
        },
        {
            "name": "天涯",
            "qq": 36937883,
            "type": 3,
            "msg": [
                "",
                "https://qqq.gtimg.cn/music/photo_new/T053XD000000NIZ4j2OUOvL.jpg",
                ""
            ]
        },
        {
            "name": "天涯",
            "qq": 36937883,
            "type": 3,
            "msg": [
                "",
                "https://qqq.gtimg.cn/music/photo_new/T053XD0000010kKvx3npRY9.jpg",
                ""
            ]
        },
        {
            "name": "天涯",
            "qq": 36937883,
            "type": 3,
            "msg": [
                "",
                "https://qqq.gtimg.cn/music/photo_new/T053XD000003uUn5m1Hhyvf.jpg",
                ""
            ]
        }
    ]
}