{
    "code": 1,
    "content": [
        {
            "name": "天涯",
            "qq": 36937883,
            "type": 3,
            "msg": [
                "渣女Y,P成瘾，自述多,人经历简直毁三观！！",
                "",
                ""
            ]
        },
        {
            "name": "天涯",
            "qq": 36937883,
            "type": 3,
            "msg": [
                "",
                "https://qqq.gtimg.cn/music/photo_new/T053XD000001aTeSp0KWuUE.png",
                ""
            ]
        },
        {
            "name": "天涯",
            "qq": 36937883,
            "type": 3,
            "msg": [
                "",
                "https://qqq.gtimg.cn/music/photo_new/T053XD000000pG5Hn339T34.jpg",
                ""
            ]
        },
        {
            "name": "天涯",
            "qq": 36937883,
            "type": 3,
            "msg": [
                "",
                "https://qqq.gtimg.cn/music/photo_new/T053XD000000KlXJW45dlGR.jpg",
                ""
            ]
        },
        {
            "name": "天涯",
            "qq": 36937883,
            "type": 3,
            "msg": [
                "",
                "https://qqq.gtimg.cn/music/photo_new/T053XD000002hmMYP3bhVrE.jpg",
                ""
            ]
        },
        {
            "name": "天涯",
            "qq": 36937883,
            "type": 3,
            "msg": [
                "",
                "https://qqq.gtimg.cn/music/photo_new/T053XD0000003MCLT2Y8Omu.jpg",
                ""
            ]
        },
        {
            "name": "天涯",
            "qq": 36937883,
            "type": 3,
            "msg": [
                "",
                "https://qqq.gtimg.cn/music/photo_new/T053XD0000038DlbV0K8Nfv.jpg",
                ""
            ]
        },
        {
            "name": "天涯",
            "qq": 36937883,
            "type": 3,
            "msg": [
                "",
                "https://qqq.gtimg.cn/music/photo_new/T053XD0000037YEip1SYdF7.jpg",
                ""
            ]
        },
        {
            "name": "天涯",
            "qq": 36937883,
            "type": 3,
            "msg": [
                "",
                "https://qqq.gtimg.cn/music/photo_new/T053XD000001caimI4OdYIl.jpg",
                ""
            ]
        },
        {
            "name": "天涯",
            "qq": 36937883,
            "type": 3,
            "msg": [
                "",
                "https://qqq.gtimg.cn/music/photo_new/T053XD000000lcZx23sKi2t.jpg",
                ""
            ]
        },
        {
            "name": "天涯",
            "qq": 36937883,
            "type": 3,
            "msg": [
                "",
                "https://qqq.gtimg.cn/music/photo_new/T053XD000000xloIo1x2a35.jpg",
                ""
            ]
        },
        {
            "name": "天涯",
            "qq": 36937883,
            "type": 3,
            "msg": [
                "",
                "https://qqq.gtimg.cn/music/photo_new/T053XD000001B11sk2eHWpG.jpg",
                ""
            ]
        },
        {
            "name": "天涯",
            "qq": 36937883,
            "type": 3,
            "msg": [
                "",
                "https://qqq.gtimg.cn/music/photo_new/T053XD0000047yjVM16JqXq.jpg",
                ""
            ]
        },
        {
            "name": "天涯",
            "qq": 36937883,
            "type": 3,
            "msg": [
                "",
                "",
                "围观传送👇<br>https://5680.net/47c5ff6cf52b62eb99269783798977568597ea14.m3u8"
            ]
        }
    ]
}