{
    "code": 1,
    "content": [
        {
            "name": "天涯",
            "qq": 36937883,
            "type": 3,
            "msg": [
                "网传12岁男孩的瓜",
                "",
                ""
            ]
        },
        {
            "name": "天涯",
            "qq": 36937883,
            "type": 3,
            "msg": [
                "",
                "https://qqq.gtimg.cn/music/photo_new/T053XD000000aaWA13aEJ9i.jpg",
                ""
            ]
        },
        {
            "name": "天涯",
            "qq": 36937883,
            "type": 3,
            "msg": [
                "",
                "https://qqq.gtimg.cn/music/photo_new/T053XD0000045mXvg4WRWHH.jpg",
                ""
            ]
        },
        {
            "name": "天涯",
            "qq": 36937883,
            "type": 3,
            "msg": [
                "",
                "https://qqq.gtimg.cn/music/photo_new/T053XD000000Niogx1iXcaz.jpg",
                ""
            ]
        },
        {
            "name": "天涯",
            "qq": 36937883,
            "type": 3,
            "msg": [
                "",
                "https://qqq.gtimg.cn/music/photo_new/T053XD0000045glQc2yjK6l.jpg",
                ""
            ]
        },
        {
            "name": "天涯",
            "qq": 36937883,
            "type": 3,
            "msg": [
                "",
                "https://qqq.gtimg.cn/music/photo_new/T053XD000000Ypjf63hXCjK.jpg",
                ""
            ]
        },
        {
            "name": "天涯",
            "qq": 36937883,
            "type": 3,
            "msg": [
                "",
                "https://qqq.gtimg.cn/music/photo_new/T053XD00000106x9F10UBT3.jpg",
                ""
            ]
        },
        {
            "name": "天涯",
            "qq": 36937883,
            "type": 3,
            "msg": [
                "",
                "https://qqq.gtimg.cn/music/photo_new/T053XD000000b4GuD12XJTS.jpg",
                ""
            ]
        },
        {
            "name": "天涯",
            "qq": 36937883,
            "type": 3,
            "msg": [
                "",
                "https://qqq.gtimg.cn/music/photo_new/T053XD0000000ZfXj1WSAEH.jpg",
                ""
            ]
        }
    ]
}